webullpaysdktrade/__init__.py
webullpaysdktrade/api.py
webullpaysdktrade/grpc_api.py
webullpaysdktrade/common/__init__.py
webullpaysdktrade/common/account_type.py
webullpaysdktrade/common/category.py
webullpaysdktrade/common/currency.py
webullpaysdktrade/common/instrument_type.py
webullpaysdktrade/common/markets.py
webullpaysdktrade/common/order_entrust_type.py
webullpaysdktrade/common/order_side.py
webullpaysdktrade/common/order_status.py
webullpaysdktrade/common/order_tif.py
webullpaysdktrade/common/order_type.py
webullpaysdktrade/common/trade_policy.py
webullpaysdktrade/events/__init__.py
webullpaysdktrade/events/types.py
webullpaysdktrade/request/__init__.py
webullpaysdktrade/request/cancel_order_request.py
webullpaysdktrade/request/get_account_balance_request.py
webullpaysdktrade/request/get_account_positions_request.py
webullpaysdktrade/request/get_account_profile_request.py
webullpaysdktrade/request/get_app_subscriptions.py
webullpaysdktrade/request/get_open_orders_request.py
webullpaysdktrade/request/get_order_detail_request.py
webullpaysdktrade/request/get_today_orders_request.py
webullpaysdktrade/request/get_tradable_instruments_request.py
webullpaysdktrade/request/palce_order_request.py
webullpaysdktrade/trade/__init__.py
webullpaysdktrade/trade/account_info.py
webullpaysdktrade/trade/order_operation.py
webullpaysdktrade/trade/trade_instrument.py
webullpay_python_sdk_trade-0.1.0.dist-info/METADATA
webullpay_python_sdk_trade-0.1.0.dist-info/WHEEL
webullpay_python_sdk_trade-0.1.0.dist-info/top_level.txt
webullpay_python_sdk_trade-0.1.0.dist-info/RECORD
